README.rst
setup.py
sagaconfig.egg-info/PKG-INFO
sagaconfig.egg-info/SOURCES.txt
sagaconfig.egg-info/dependency_links.txt
sagaconfig.egg-info/top_level.txt
src/__about__.py
src/__init__.py
test/test_config.py