Metadata-Version: 1.1
Name: sagaconfig
Version: 0.0.4
Summary: A config helper.
Home-page: https://github.com/Sagacify/config-py
Author: Sagacify
Author-email: dev+python@sagacify.com
License: MIT
Platform: UNKNOWN
Classifier: Development Status :: 4 - Beta
Classifier: License :: OSI Approved :: MIT License
Classifier: Programming Language :: Python :: 3.5
